Metadata-Version: 1.1
Name: protobuf-to-dict-2
Version: 0.1.0
Summary: A teeny Python library for creating Python dicts from protocol buffers and the reverse. Useful as an intermediate step before serialisation (e.g. to JSON).
Home-page: https://github.com/mkhizeryounas/protobuf-to-dict
Author: Khizer Younas
Author-email: m.khizeryounas@gmail.com
License: Public Domain
Keywords: protobuf,json,dict
Platform: UNKNOWN
Classifier: Programming Language :: Python
Classifier: Development Status :: 4 - Beta
Classifier: Intended Audience :: Developers
Classifier: License :: Public Domain
Classifier: Operating System :: OS Independent
Classifier: Topic :: Software Development :: Libraries :: Python Modules
